bech32/__init__.py
bech32/py.typed
bech32-1.2.0.dist-info/LICENSE
bech32-1.2.0.dist-info/METADATA
bech32-1.2.0.dist-info/WHEEL
bech32-1.2.0.dist-info/top_level.txt
bech32-1.2.0.dist-info/RECORD
