Metadata-Version: 2.1
Name: bech32
Version: 1.2.0
Summary: Reference implementation for Bech32 and segwit addresses.
Home-page: https://github.com/fiatjaf/bech32
Maintainer: fiatjaf
Maintainer-email: fiatjaf@alhur.es
License: MIT
Platform: UNKNOWN
Classifier: License :: OSI Approved :: MIT License
Classifier: Programming Language :: Python :: 3
Classifier: Programming Language :: Python :: 3.7
Requires-Python: >=3.5
